BToolbox/__init__.py
BToolbox/__main__.py
btoolbox-0.1.0.dist-info/METADATA
btoolbox-0.1.0.dist-info/WHEEL
btoolbox-0.1.0.dist-info/RECORD
